pyvas/__init__.py
pyvas/client.py
pyvas/exceptions.py
pyvas/response.py
pyvas/utils.py
pyvas-0.4.0.dist-info/DESCRIPTION.rst
pyvas-0.4.0.dist-info/METADATA
pyvas-0.4.0.dist-info/RECORD
pyvas-0.4.0.dist-info/WHEEL
pyvas-0.4.0.dist-info/metadata.json
pyvas-0.4.0.dist-info/top_level.txt
