Metadata-Version: 2.0
Name: pyvas
Version: 0.4.0
Summary: An OpenVAS Managment Protocol (OMP) v7 client for Python
Home-page: https://github.com/mpicard/pyvas
Author: Martin Picard
Author-email: martin8768@gmail.com
License: MIT
Keywords: openvas omp client
Platform: UNKNOWN
Classifier: Development Status :: 4 - Beta
Classifier: Intended Audience :: Developers
Classifier: Operating System :: Unix
Classifier: License :: OSI Approved :: MIT License
Classifier: Programming Language :: Python :: 2
Classifier: Programming Language :: Python :: 2.7
Classifier: Programming Language :: Python :: 3
Classifier: Programming Language :: Python :: 3.5
Classifier: Programming Language :: Python :: 3.6
Classifier: Programming Language :: Python :: Implementation :: CPython
Classifier: Topic :: Utilities
Classifier: Topic :: Software Development :: Libraries
Classifier: Topic :: Internet :: WWW/HTTP
Requires-Dist: lxml
Requires-Dist: six
